pyvscpudp-0.0.2.data/data/my_data/data_file
sample/__init__.py
sample/package_data.dat
vscp/__init__.py
vscp/multicast.py
vscp/tcpip.py
vscp/testguid.py
vscp/testudp.py
vscp/testvscphelper.py
vscp/udp.py
vscp/vscp.py
vscp/vscp_class.py
vscp/vscp_type.py
vscp/vscphelper.py
pyvscpudp-0.0.2.dist-info/LICENSE
pyvscpudp-0.0.2.dist-info/LICENSE.txt
pyvscpudp-0.0.2.dist-info/METADATA
pyvscpudp-0.0.2.dist-info/WHEEL
pyvscpudp-0.0.2.dist-info/entry_points.txt
pyvscpudp-0.0.2.dist-info/top_level.txt
pyvscpudp-0.0.2.dist-info/RECORD
