Metadata-Version: 2.1
Name: pyvscpudp
Version: 0.0.2
Summary: Official VSCP UDP Python package
Home-page: https://github.com/grodansparadis/pyvscpudp
Author: Ake Hedman, Grodans Paradis AB
Author-email: akhe@grodansparadis.com
License: MIT
Keywords: vscp iot m2m automation development
Platform: UNKNOWN
Classifier: Development Status :: 3 - Alpha
Classifier: Intended Audience :: Developers
Classifier: Topic :: Software Development :: Build Tools
Classifier: License :: OSI Approved :: MIT License
Classifier: Programming Language :: Python :: 3
Classifier: Programming Language :: Python :: 3.3
Classifier: Programming Language :: Python :: 3.4
Classifier: Programming Language :: Python :: 3.5
Classifier: Programming Language :: Python :: 3.6
Classifier: Programming Language :: Python :: 3.7
Classifier: Programming Language :: Python :: 3.8
Classifier: Programming Language :: Python :: 3.9
Requires-Python: >=3.0
Requires-Dist: pyvscp
Requires-Dist: pythoncrc
Requires-Dist: crypto
Provides-Extra: dev
Requires-Dist: check-manifest ; extra == 'dev'
Provides-Extra: test
Requires-Dist: coverage ; extra == 'test'
